README.txt
setup.py
dse/__init__.py
dse/singleton.py
dse.egg-info/PKG-INFO
dse.egg-info/SOURCES.txt
dse.egg-info/dependency_links.txt
dse.egg-info/top_level.txt