Metadata-Version: 1.1
Name: dse
Version: 4.0.0-RC1
Summary: DSE - Simplified "bulk" insert/update/delete for Django.
Home-page: https://bitbucket.org/weholt/dse4
Author: Thomas Weholt
Author-email: thomas@weholt.org
License: UNKNOWN
Platform: UNKNOWN
Classifier: Development Status :: 4 - Beta
Classifier: Intended Audience :: Developers
Classifier: Framework :: Django
Classifier: License :: OSI Approved :: BSD License
Classifier: Operating System :: OS Independent
Classifier: Programming Language :: Python
Classifier: Topic :: Database
